{
  "owner": "Rod",
  "updated": "2026-06-25T23:39:03",
  "group_results": {
    "1": {
      "outcome": "1"
    },
    "2": {
      "outcome": "X"
    },
    "3": {
      "outcome": "1"
    },
    "4": {
      "outcome": "X"
    },
    "5": {
      "outcome": "1"
    },
    "6": {
      "outcome": "1"
    },
    "7": {
      "outcome": "1"
    },
    "8": {
      "outcome": "2"
    },
    "9": {
      "outcome": "1"
    },
    "10": {
      "outcome": "1"
    },
    "11": {
      "outcome": "1"
    },
    "12": {
      "outcome": "1"
    },
    "61": {
      "outcome": "1"
    },
    "13": {
      "outcome": "1"
    },
    "14": {
      "outcome": "2"
    },
    "15": {
      "outcome": "1"
    },
    "16": {
      "outcome": "1"
    },
    "17": {
      "outcome": "1"
    },
    "18": {
      "outcome": "2"
    },
    "19": {
      "outcome": "1"
    },
    "20": {
      "outcome": "2"
    },
    "21": {
      "outcome": "1"
    },
    "22": {
      "outcome": "1"
    },
    "23": {
      "outcome": "X"
    },
    "24": {
      "outcome": "1"
    },
    "25": {
      "outcome": "1"
    },
    "26": {
      "outcome": "2"
    },
    "27": {
      "outcome": "X"
    },
    "28": {
      "outcome": "1"
    },
    "29": {
      "outcome": "1"
    },
    "30": {
      "outcome": "2"
    },
    "31": {
      "outcome": "1"
    },
    "32": {
      "outcome": "2"
    },
    "33": {
      "outcome": "1"
    },
    "34": {
      "outcome": "1"
    },
    "35": {
      "outcome": "1"
    },
    "36": {
      "outcome": "2"
    },
    "37": {
      "outcome": "1"
    },
    "38": {
      "outcome": "1"
    },
    "39": {
      "outcome": "2"
    },
    "40": {
      "outcome": "1"
    },
    "41": {
      "outcome": "2"
    },
    "42": {
      "outcome": "2"
    },
    "43": {
      "outcome": "1"
    },
    "44": {
      "outcome": "X"
    },
    "45": {
      "outcome": "2"
    },
    "46": {
      "outcome": "1"
    },
    "47": {
      "outcome": "2"
    },
    "48": {
      "outcome": "1"
    },
    "49": {
      "outcome": "1"
    },
    "50": {
      "outcome": "1"
    },
    "51": {
      "outcome": "1"
    },
    "52": {
      "outcome": "1"
    },
    "53": {
      "outcome": "1"
    },
    "54": {
      "outcome": "2"
    },
    "55": {
      "outcome": "1"
    },
    "56": {
      "outcome": "1"
    },
    "57": {
      "outcome": "1"
    },
    "58": {
      "outcome": "1"
    },
    "59": {
      "outcome": "X"
    },
    "60": {
      "outcome": "2"
    },
    "62": {
      "outcome": "2"
    },
    "63": {
      "outcome": "1"
    },
    "64": {
      "outcome": "1"
    },
    "65": {
      "outcome": "1"
    },
    "66": {
      "outcome": "2"
    },
    "67": {
      "outcome": "1"
    },
    "68": {
      "outcome": "1"
    },
    "69": {
      "outcome": "1"
    },
    "70": {
      "outcome": "2"
    },
    "71": {
      "outcome": "2"
    },
    "72": {
      "outcome": "1"
    }
  },
  "third_assignments": {
    "74:t2": "Suecia",
    "77:t2": "Paraguay",
    "79:t2": "Ecuador",
    "80:t2": "Austria"
  },
  "ko_winners": {
    "73": "México",
    "76": "Brasil",
    "74": "Alemania",
    "75": "Países Bajos",
    "77": "Francia",
    "78": "Senegal",
    "79": "Chequia",
    "80": "Inglaterra",
    "83": "Colombia",
    "84": "España",
    "86": "Argentina",
    "89": "Francia"
  },
  "variables": {
    "1": {
      "t1": "Gol de Raul Jimenez",
      "v1": "si",
      "t2": "Grito de Puto si o no?",
      "v2": "no",
      "t3": "Habrá gol anulado por el var?",
      "v3": "no",
      "t4": "Gol en los ultimos 8 minutos",
      "v4": "no",
      "marcador": "3-1"
    },
    "3": {
      "t1": "Habrá gol anulado por el VAR?",
      "v1": "SI",
      "t2": "Habrá autogol?",
      "v2": "No",
      "t3": "Over de 2 goles en primer tiempo",
      "v3": "no",
      "t4": "",
      "v4": "",
      "marcador": "2-0"
    },
    "66": {
      "t1": "Gol en los primeros 13 minutos si o no",
      "v1": "Si",
      "t2": "Goles de tiro de esquina Si o No, vale Doble",
      "v2": "Si",
      "t3": "Habrá Hat Trick?",
      "v3": "No",
      "t4": "",
      "v4": "",
      "marcador": "3-0"
    },
    "67": {
      "t1": "Gol de Kane?",
      "v1": "Si",
      "t2": "Marcador al medio tiempo",
      "v2": "0 - 0",
      "t3": "Habrá gol de cabeza?",
      "v3": "No",
      "t4": "",
      "v4": "",
      "marcador": "1 - 0"
    },
    "68": {
      "t1": "En que minuto cae el primer gol? vale triple",
      "v1": "9",
      "t2": "Mas de 1 gol en los ultimos 16 minutos",
      "v2": "No",
      "t3": "Que jugador anota el primer gol?",
      "v3": "Antoine Semenyo",
      "t4": "",
      "v4": "",
      "marcador": "2-1"
    },
    "65": {
      "t1": "Marcador al medio tiempo",
      "v1": "2-0",
      "t2": "Gol en los últimos 3 minutos",
      "v2": "No",
      "t3": "Gol en los primeros 9 minutos",
      "v3": "Si",
      "t4": "",
      "v4": "",
      "marcador": "3-1"
    },
    "9": {
      "t1": "goles de tiro libre",
      "v1": "1",
      "t2": "habra penales?",
      "v2": "no",
      "t3": "goles en el segundo tiempo",
      "v3": "2",
      "t4": "",
      "v4": "",
      "marcador": "3-0"
    },
    "10": {
      "t1": "Over de 4 amarillas",
      "v1": "Si",
      "t2": "Goles de tiro libre",
      "v2": "No",
      "t3": "Gol entre el minuto 60 y 70. Vale doble",
      "v3": "Si",
      "t4": "",
      "v4": "",
      "marcador": "2-1"
    },
    "4": {
      "t1": "Habrá grito de puto?",
      "v1": "No",
      "t2": "Marcador al medio tiempo",
      "v2": "0-1",
      "t3": "Gol entre el minuto 35 y 45. vale doble",
      "v3": "Si",
      "t4": "Expulsion DT",
      "v4": "No",
      "marcador": "2-2"
    },
    "22": {
      "t1": "Gol entre el minuto 81 y 90 Vale Triple",
      "v1": "Si",
      "t2": "Tarjetas Rojas",
      "v2": "No",
      "t3": "Jugará Australia con uniforme Verde/rosa?",
      "v3": "Verde",
      "t4": "",
      "v4": "",
      "marcador": "3-1"
    },
    "15": {
      "t1": "Marcador al Medio tiempo",
      "v1": "2-0",
      "t2": "Goles en el segundo tiempo, cuantos? vale doble",
      "v2": "1",
      "t3": "Over de 4 goles, si o no",
      "v3": "No",
      "t4": "",
      "v4": "",
      "marcador": "3-0"
    },
    "25": {
      "t1": "Goles de Cabeza en el primer tiempo",
      "v1": "Si",
      "t2": "Over de 4 goles",
      "v2": "Si",
      "t3": "Gol de algun defensa",
      "v3": "No",
      "t4": "",
      "v4": "",
      "marcador": "4-1"
    },
    "26": {
      "t1": "Marcador al minuto 38",
      "v1": "0-2",
      "t2": "Goles de tiro libre",
      "v2": "no, 0",
      "t3": "Over de 5 amarillas",
      "v3": "no",
      "t4": "",
      "v4": "",
      "marcador": "0-3"
    },
    "54": {
      "t1": "Más de 2 goles de Mbappe. Sí o no.",
      "v1": "Si",
      "t2": "Gol en los primeros 6 minutos. Sí o no",
      "v2": "No",
      "t3": "Over de 6 goles totales. Sí o no.",
      "v3": "no",
      "t4": "",
      "v4": "",
      "marcador": "1 - 4"
    },
    "57": {
      "t1": "Over de 3 goles si o no",
      "v1": "Si",
      "t2": "Gol entre minuto 15 y 33",
      "v2": "Si",
      "t3": "Gol despues del minuto 86",
      "v3": "No",
      "t4": "",
      "v4": "",
      "marcador": "2 - 1"
    },
    "64": {
      "t1": "¿Cuantos goles antes del medio tiempo?",
      "v1": "2",
      "t2": "Marcador al minuto 47",
      "v2": "2 - 0",
      "t3": "⁠¿Habrá penales?",
      "v3": "No",
      "t4": "",
      "v4": "",
      "marcador": "3 - 0"
    },
    "69": {
      "t1": "¿Cuantos goles totales en los primeros 31 minutos? Vale triple",
      "v1": "2",
      "t2": "¿Gol de tiro libre?",
      "v2": "Si",
      "t3": "Over de 5 amarillas. Sí o no.",
      "v3": "Si",
      "t4": "",
      "v4": "",
      "marcador": "2-1"
    },
    "70": {
      "t1": "Marcador al medio tiempo. Vale doble",
      "v1": "0 - 2",
      "t2": "Gol entre el minuto 29 y 48. Sí o no.",
      "v2": "Si",
      "t3": "Gol de algún jugador que no sea delantero. Sí o no",
      "v3": "Si",
      "t4": "",
      "v4": "",
      "marcador": "1 - 3"
    },
    "63": {
      "t1": "Amarillas para cuerpo técnico? Si o no",
      "v1": "Si",
      "t2": "Cuantos Goles totales",
      "v2": "3",
      "t3": "Que equipo cometerá mas faltas?",
      "v3": "Colombia",
      "t4": "",
      "v4": "",
      "marcador": "2 - 1"
    },
    "11": {
      "t1": "Gol en los primeros 28 minutos",
      "v1": "No",
      "t2": "Habrá algún expulsado",
      "v2": "No",
      "t3": "Algún gol después del minuto 88? Vale doble",
      "v3": "No",
      "t4": "",
      "v4": "",
      "marcador": "0 - 1"
    },
    "12": {
      "t1": "Gol en los primeros 28 minutos",
      "v1": "si",
      "t2": "Habrá algún expulsado",
      "v2": "no",
      "t3": "Algún gol después del minuto 88? Vale doble",
      "v3": "no",
      "t4": "",
      "v4": "",
      "marcador": "3 - 0"
    },
    "17": {
      "t1": "Gol en los primeros 28 minutos",
      "v1": "si",
      "t2": "Habrá algún expulsado",
      "v2": "no",
      "t3": "Algún gol después del minuto 88? Vale doble",
      "v3": "no",
      "t4": "",
      "v4": "",
      "marcador": "2 - 0"
    },
    "18": {
      "t1": "Ganador vence por más de 1 gol? Sí o no.",
      "v1": "si",
      "t2": "Over de 4 goles totales?",
      "v2": "no",
      "t3": "Gol entre el minuto 45 y 51 (2do. tiempo)? Vale doble",
      "v3": "no",
      "t4": "",
      "v4": "",
      "marcador": "1 - 3"
    },
    "6": {
      "t1": "Ganador vence por más de 1 gol? Sí o no.",
      "v1": "si",
      "t2": "Over de 4 goles totales?",
      "v2": "Si",
      "t3": "Gol entre el minuto 45 y 51 (2do. tiempo)? Vale doble",
      "v3": "No",
      "t4": "",
      "v4": "",
      "marcador": "1 - 4"
    },
    "5": {
      "t1": "Ganador vence por más de 1 gol? Sí o no.",
      "v1": "si",
      "t2": "Over de 4 goles totales?",
      "v2": "no",
      "t3": "Gol entre el minuto 45 y 51 (2do. tiempo)? Vale doble",
      "v3": "si",
      "t4": "",
      "v4": "",
      "marcador": "1 - 2"
    },
    "30": {
      "t1": "Gol de Undav. Sí o no.",
      "v1": "Si",
      "t2": "¿Marcador en ceros al medio?",
      "v2": "No",
      "t3": "¿Qué equipo tendrá más tiros a puerta?",
      "v3": "Alemania",
      "t4": "",
      "v4": "",
      "marcador": "0 - 2"
    },
    "29": {
      "t1": "En qué minuto cae el primer gol? Vale triple",
      "v1": "32",
      "t2": "Over de 4 goles totales. Sí o no",
      "v2": "no",
      "t3": "Gol en los últimos 9 minutos. Sí o no",
      "v3": "no",
      "t4": "",
      "v4": "",
      "marcador": "2 - 1"
    },
    "34": {
      "t1": "Gol en los primeros 13 mins",
      "v1": "No",
      "t2": "Gol de cabeza",
      "v2": "No",
      "t3": "Habrá doblete de un jugador",
      "v3": "Si",
      "t4": "",
      "v4": "",
      "marcador": "4 - 2"
    },
    "33": {
      "t1": "Que equipo anota primero",
      "v1": "Japon",
      "t2": "Habrá penales marcados",
      "v2": "No",
      "t3": "Goles de tiro de esquina máximo, 3 toques totales",
      "v3": "Si",
      "t4": "",
      "v4": "",
      "marcador": "3 - 2"
    },
    "24": {
      "t1": "Gol antes del min 20 si o no",
      "v1": "No",
      "t2": "Mas de 4 goles si o no",
      "v2": "No",
      "t3": "Algún equipo con mas de 3 amarillas",
      "v3": "Si",
      "t4": "",
      "v4": "",
      "marcador": "1 - 1"
    },
    "23": {
      "t1": "Gol de algun delantero",
      "v1": "Si - Folarin Balogun",
      "t2": "Marcador al medio tiempo",
      "v2": "1 - 1",
      "t3": "Gol después del min 87",
      "v3": "",
      "t4": "",
      "v4": "",
      "marcador": "2 - 2"
    }
  }
}